cppm/__init__.py
cppm/add_command.py
cppm/build_command.py
cppm/create_starter_project.py
cppm/init_command.py
cppm/install_command.py
cppm/new_command.py
cppm/utils.py
cppm/vcpkg.py
cppm-0.1.5.dist-info/METADATA
cppm-0.1.5.dist-info/WHEEL
cppm-0.1.5.dist-info/entry_points.txt
cppm-0.1.5.dist-info/RECORD
