Metadata-Version: 2.3
Name: cppm
Version: 0.1.5
Summary: A CLI helper tool for managing C++ projects
License: MIT
Author: Kape
Author-email: kleberkapelinski@gmail.com
Requires-Python: >=3.9
Classifier: License :: OSI Approved :: MIT License
Classifier: Programming Language :: Python :: 3
Classifier: Programming Language :: Python :: 3.9
Classifier: Programming Language :: Python :: 3.10
Classifier: Programming Language :: Python :: 3.11
Classifier: Programming Language :: Python :: 3.12
Classifier: Programming Language :: Python :: 3.13
